pirs/__init__.py
pirs/core/__init__.py
pirs/core/test_tramat.py
pirs/core/scheduler/__init__.py
pirs/core/scheduler/_example_wp.py
pirs/core/scheduler/empi2.py
pirs/core/scheduler/ex1.py
pirs/core/scheduler/scheduler.py
pirs/core/scheduler/workplace.py
pirs/core/scheduler/workplaces.py
pirs/core/trageom/__init__.py
pirs/core/trageom/_experimental.py
pirs/core/trageom/vector.py
pirs/core/tramat/__init__.py
pirs/core/tramat/_printoutfile.py
pirs/core/tramat/_xsdir.py
pirs/core/tramat/chemical_formulae.py
pirs/core/tramat/data_masses.py
pirs/core/tramat/data_names.py
pirs/core/tramat/data_natural.py
pirs/core/tramat/mixer.py
pirs/core/tramat/natural.py
pirs/core/tramat/tmp.py
pirs/hli/__init__.py
pirs/hli/mcnp/__init__.py
pirs/hli/mcnp/convertors.py
pirs/hli/mcnp/interface.py
pirs/hli/scf2/__init__.py
pirs/hli/scf2/convertors.py
pirs/hli/scf2/interface.py
pirs/mcnp/__init__.py
pirs/mcnp/_sab.py
pirs/mcnp/_uncert.py
pirs/mcnp/cad_vols.py
pirs/mcnp/cad_vols_example.py
pirs/mcnp/card_classes.py
pirs/mcnp/cells.py
pirs/mcnp/ewf.py
pirs/mcnp/formatter.py
pirs/mcnp/isocomps.py
pirs/mcnp/material.py
pirs/mcnp/mctal.py
pirs/mcnp/model.py
pirs/mcnp/outp.py
pirs/mcnp/read_mctal.py
pirs/mcnp/read_mctal5.py
pirs/mcnp/surfaces.py
pirs/mcnp/tallies.py
pirs/mcnp/workplace.py
pirs/mcnp/xsdir.py
pirs/mcnp/auxiliary/__init__.py
pirs/mcnp/auxiliary/counters.py
pirs/mcnp/auxiliary/xs_interpolation.py
pirs/scf2/__init__.py
pirs/scf2/_example.py
pirs/scf2/defaults.py
pirs/scf2/input.py
pirs/scf2/input_help.py
pirs/scf2/material.py
pirs/scf2/output.py
pirs/scf2/template25.py
pirs/scf2/variables.py
pirs/scf2/workplace.py
pirs/scf3/_example_bwr.py
pirs/scf3/_example_hex.py
pirs/scf3/_example_mini_bwr.py
pirs/scf3/_example_plots.py
pirs/scf3/_rpoly_test.py
pirs/scf3/model.py
pirs/scf3/qhull_interface.py
pirs/solids/__init__.py
pirs/solids/functions.py
pirs/solids/intersections.py
pirs/solids/positions.py
pirs/solids/reports.py
pirs/solids/set_properties_as_kw.py
pirs/solids/solids3.py
pyirs-0.1.4.dist-info/LICENSE
pyirs-0.1.4.dist-info/METADATA
pyirs-0.1.4.dist-info/WHEEL
pyirs-0.1.4.dist-info/entry_points.txt
pyirs-0.1.4.dist-info/top_level.txt
pyirs-0.1.4.dist-info/RECORD
