Metadata-Version: 2.1
Name: pyirs
Version: 0.1.4
Summary: Python Interfaces for Reactor Simulations
Home-page: https://github.com/inr-kit/pirs2
Author: Anton Travleev
Author-email: anton.travleev@gmail.com
License: UNKNOWN
Keywords: MCNP SCF COUPLED REACTOR CALCULATIONS
Platform: UNKNOWN
Classifier: Development Status :: 4 - Beta
Classifier: Environment :: Console
Classifier: Intended Audience :: Science/Research
Classifier: Intended Audience :: Education
Classifier: License :: OSI Approved :: GNU General Public License v3 (GPLv3)
Classifier: Programming Language :: Python :: 2.7
Classifier: Topic :: Scientific/Engineering
Provides: pirs
Requires-Dist: uncertainties (==2.4.4)
